<?xml version="1.0" encoding="UTF-8"?>
<con:testCase id="ba08b677-eb09-4787-a670-a1a1a5b5783f" discardOkResults="true" failOnError="true" failTestCaseOnErrors="true" keepSession="false" name="Display single product confirmation business interaction" searchProperties="true" timeout="0" xmlns:con="http://eviware.com/soapui/config">
  <con:settings>
    <con:setting id="ba08b677-eb09-4787-a670-a1a1a5b5783ffileName">Display-single-product-confirmation-business-interaction</con:setting>
  </con:settings>
  <con:savedRecentRuns>1</con:savedRecentRuns>
  <con:testStep type="restrequest" name="Display single product confirmation business interaction" id="d95d47f6-a77e-4088-994c-c178fa0e0528">
    <con:settings/>
    <con:config service="ERMS API" resourcePath="/productConfirmation/{biId}" methodName="Method 1" xsi:type="con:RestRequestStep" xmlns:xsi="http://www.w3.org/2001/XMLSchema-instance">
      <con:restRequest name="Display single product confirmation business interaction" id="99966c56-7808-47a2-83b3-c519e6ae1336" mediaType="application/json">
        <con:settings>
          <con:setting id="com.eviware.soapui.impl.wsdl.WsdlRequest@request-headers">&lt;xml-fragment/></con:setting>
        </con:settings>
        <con:endpoint>${#Project#ExtEndpoint}</con:endpoint>
        <con:request/>
        <con:credentials>
          <con:selectedAuthProfile>No Authorization</con:selectedAuthProfile>
          <con:authType>No Authorization</con:authType>
        </con:credentials>
        <con:jmsConfig JMSDeliveryMode="PERSISTENT"/>
        <con:parameters>
          <entry key="biId" value="${#TestCase#req_biId}" xmlns="http://eviware.com/soapui/config"/>
        </con:parameters>
      </con:restRequest>
    </con:config>
  </con:testStep>
  <con:testStep type="transfer" name="Property Transfer" id="6668c33e-f846-4f85-ae75-4596e29be59b">
    <con:settings/>
    <con:config xsi:type="con:PropertyTransfersStep" xmlns:xsi="http://www.w3.org/2001/XMLSchema-instance">
      <con:transfers setNullOnMissingSource="true" transferTextContent="true" failOnError="true" ignoreEmpty="false" transferToAll="false" entitize="false" transferChildNodes="false">
        <con:name>biId</con:name>
        <con:sourceType>Response</con:sourceType>
        <con:sourceStep>Display single product confirmation business interaction</con:sourceStep>
        <con:sourcePath>$['id']</con:sourcePath>
        <con:targetType>req_biId</con:targetType>
        <con:targetStep>#TestCase#</con:targetStep>
        <con:targetPath/>
        <con:type>JSONPATH</con:type>
        <con:upgraded>true</con:upgraded>
      </con:transfers>
      <con:transfers setNullOnMissingSource="true" transferTextContent="true" failOnError="true" ignoreEmpty="false" transferToAll="false" entitize="false" transferChildNodes="false">
        <con:name>state</con:name>
        <con:sourceType>Response</con:sourceType>
        <con:sourceStep>Display single product confirmation business interaction</con:sourceStep>
        <con:sourcePath>$['state']</con:sourcePath>
        <con:targetType>res_state</con:targetType>
        <con:targetStep>#TestCase#</con:targetStep>
        <con:type>JSONPATH</con:type>
        <con:upgraded>true</con:upgraded>
      </con:transfers>
      <con:transfers setNullOnMissingSource="true" transferTextContent="true" failOnError="true" ignoreEmpty="false" transferToAll="false" entitize="false" transferChildNodes="false">
        <con:name>mainState</con:name>
        <con:sourceType>Response</con:sourceType>
        <con:sourceStep>Display single product confirmation business interaction</con:sourceStep>
        <con:sourcePath>$['mainState']</con:sourcePath>
        <con:targetType>res_mainState</con:targetType>
        <con:targetStep>#TestCase#</con:targetStep>
        <con:type>JSONPATH</con:type>
        <con:upgraded>true</con:upgraded>
      </con:transfers>
      <con:transfers setNullOnMissingSource="true" transferTextContent="true" failOnError="true" ignoreEmpty="false" transferToAll="false" entitize="false" transferChildNodes="false">
        <con:name>code</con:name>
        <con:sourceType>HarResponse</con:sourceType>
        <con:sourceStep>Display single product confirmation business interaction</con:sourceStep>
        <con:sourcePath>$['status']</con:sourcePath>
        <con:targetType>res_code</con:targetType>
        <con:targetStep>#TestCase#</con:targetStep>
        <con:type>JSONPATH</con:type>
        <con:upgraded>true</con:upgraded>
      </con:transfers>
      <con:transfers setNullOnMissingSource="true" transferTextContent="true" failOnError="true" ignoreEmpty="false" transferToAll="false" entitize="false" transferChildNodes="false">
        <con:name>description</con:name>
        <con:sourceType>Response</con:sourceType>
        <con:sourceStep>Display single product confirmation business interaction</con:sourceStep>
        <con:sourcePath>$['description']</con:sourcePath>
        <con:targetType>res_description</con:targetType>
        <con:targetStep>#TestCase#</con:targetStep>
        <con:type>JSONPATH</con:type>
        <con:upgraded>true</con:upgraded>
      </con:transfers>
    </con:config>
  </con:testStep>
  <con:properties>
    <con:property>
      <con:name>req_biId</con:name>
      <con:value/>
    </con:property>
    <con:property>
      <con:name>res_biId</con:name>
      <con:value/>
    </con:property>
    <con:property>
      <con:name>res_code</con:name>
      <con:value/>
    </con:property>
    <con:property>
      <con:name>res_description</con:name>
      <con:value/>
    </con:property>
    <con:property>
      <con:name>res_state</con:name>
      <con:value/>
    </con:property>
    <con:property>
      <con:name>res_mainState</con:name>
      <con:value/>
    </con:property>
  </con:properties>
  <con:reportParameters/>
</con:testCase>